rpa_monitor_client/__init__.py
rpa_monitor_client/_client.py
rpa_monitor_client/_commands.py
rpa_monitor_client/_config.py
rpa_monitor_client/_logging_api.py
rpa_monitor_client-0.1.1.dist-info/METADATA
rpa_monitor_client-0.1.1.dist-info/WHEEL
rpa_monitor_client-0.1.1.dist-info/top_level.txt
rpa_monitor_client-0.1.1.dist-info/RECORD
