Metadata-Version: 2.4
Name: rpa-monitor-client
Version: 0.1.1
Summary: Cliente RPA para enviar heartbeats, logs e comandos para servidor de monitoramento (TCP/WebSocket)
Author-email: Andrey Barreto <andrey@inovailab.com>
License: MIT
Project-URL: Homepage, https://inovailab.com
Classifier: Programming Language :: Python :: 3
Classifier: Operating System :: OS Independent
Requires-Python: >=3.8
Requires-Dist: websockets>=12.0
Requires-Dist: croniter>=1.4.0
